{
  "english": "patch",
  "phat_am": "pӕtʃ",
  "list_english": [
    {
      "type_word": "noun",
      "list_definition": [
        {
          "mean_english": "miếng vá",
          "definition": "a piece of material sewn on to cover a hole",
          "world_new": [
            "piece",
            "material",
            "cover",
            "hole"
          ],
          "list_ex_of_definition": [
            {
              "ex_of_definition": "She sewed a patch on the knee of her jeans.",
              "world_new": [
                "knee",
                "jeans"
              ]
            }
          ]
        },
        {
          "mean_english": "khoảng đất nhỏ",
          "definition": "a small piece of ground",
          "world_new": [
            "small",
            "piece",
            "ground"
          ],
          "list_ex_of_definition": [
            {
              "ex_of_definition": "a vegetable patch.",
              "world_new": [
                "vegetable"
              ]
            }
          ]
        }
      ]
    },
    {
      "type_word": "verb",
      "list_definition": [
        {
          "mean_english": "vá",
          "definition": "to mend (clothes etc) by sewing on pieces of material",
          "world_new": [
            "mend",
            "sewing",
            "material"
          ],
          "list_ex_of_definition": [
            {
              "ex_of_definition": "She patched the (hole in the) child’s trousers.",
              "world_new": [
                "trousers"
              ]
            }
          ]
        }
      ]
    }
  ],
  "list_ex_of_english": [
    "The patches were clearly visible when looking up at the underside of the floor.",
    "The exterior face is l -gonal, where l is the length of the boundary of the patch.",
    "It is recognized that this monocusp does not last for very long, in that it tends to adhere to the outflow patch.",
    "Any patch of positive symbols is forced to be surrounded by on the top and bottom and on the left and right.",
    "This requires natural enemies to eliminate sparsely distributed patches of prey, so that prey spatial distribution is very relevant to the success of biological control.",
    "This density was used to define \"standard patches\" measured in arbors from binocularly deprived animals.",
    "Two-dimensional singular surfaces generated by different sets of four constraint equations intersect at many onedimensional curves that divide the surfaces into many two-dimensional patches.",
    "The repair consisted of double patch closure of the septal defect, reconstruction of two atrioventricular orifices, and relief of pulmonary stenosis at all levels."
  ],
  "list_see_also": [
    "patchy",
    "patchiness",
    "patchwork",
    "patch up"
  ],
  "list_browse": [
    "pastry",
    "pasture",
    "pasty",
    "pat",
    "patch",
    "patch up",
    "patchiness",
    "patchwork",
    "patchy"
  ],
  "list_img": [
    {
      "link_thumb": "https://live.staticflickr.com/65535/51809683734_f01afbbd0b_n.jpg",
      "link_img": "https://live.staticflickr.com/65535/51809683734_721c47b612_o.png",
      "id_image": "patch_401554"
    },
    {
      "link_thumb": "https://live.staticflickr.com/65535/51810065495_f0476093b8_n.jpg",
      "link_img": "https://live.staticflickr.com/65535/51810065495_02ff8b3657_o.png",
      "id_image": "patch_4299245"
    },
    {
      "link_thumb": "https://live.staticflickr.com/65535/51810065430_450dc6b816_n.jpg",
      "link_img": "https://live.staticflickr.com/65535/51810065430_9e3f543a3c_o.png",
      "id_image": "patch_4539324"
    },
    {
      "link_thumb": "https://live.staticflickr.com/65535/51810065370_2ff98098f4_n.jpg",
      "link_img": "https://live.staticflickr.com/65535/51810065370_9307677df0_o.png",
      "id_image": "patch_6147341"
    }
  ]
}