{
  "english": "pedestal",
  "phat_am": "ˈpedistl",
  "list_english": [
    {
      "type_word": "noun",
      "list_definition": [
        {
          "mean_english": "bệ",
          "definition": "the foot or base of a column, statue etc",
          "world_new": [
            "foot",
            "base",
            "column",
            "statue"
          ],
          "list_ex_of_definition": [
            {
              "ex_of_definition": "The statue fell off its pedestal.",
              "world_new": [
                "statue",
                "fell",
                "its"
              ]
            }
          ]
        }
      ]
    }
  ],
  "list_ex_of_english": [
    "After the park's re-design, the archway sign, elephants and columns were removed, whereas the repainted pedestals remained.",
    "The rearrangement of clothing, furniture, pedestals or monitors plays a decisive role in his oeuvre, even became independent and exposes given situations to unbiased observation.",
    "The presence of pedestal bases is also a feature that argues for a rulership interpretation of potbelly sculptures.",
    "The experimental session lasted from 45 to 90 min and comprised five blocks, one for each condition pulse-brighter pedestals, pulse-darker pedestals, zero pedestals, steady-brighter pedestals, steady-darker pedestals!.",
    "The main entrance is flanked by paired columns on pedestals and the smaller side doors are topped with semicircular pediments.",
    "The people didn't put them on their pedestals they put themselves there.",
    "The pulpit itself is a raised wooden platform supporting a lectern flanked by pedestals.",
    "Nineteen pedestals were built to install the displaced statues but only five are fixed, while the remaining plinths are vacant."
  ],
  "list_see_also": [],
  "list_browse": [
    "pedantic",
    "pedantically",
    "pedantry",
    "peddle",
    "pedestal",
    "pedestrian",
    "pedestrian crossing",
    "pedestrian precinct",
    "pedigree"
  ],
  "list_img": [
    {
      "link_thumb": "https://live.staticflickr.com/65535/51809679334_dfcd5ce09b_n.jpg",
      "link_img": "https://live.staticflickr.com/65535/51809679334_69f5aa098b_o.png",
      "id_image": "pedestal_1054096"
    },
    {
      "link_thumb": "https://live.staticflickr.com/65535/51809324076_4da6f1b0f5_n.jpg",
      "link_img": "https://live.staticflickr.com/65535/51809324076_24b955a691_o.png",
      "id_image": "pedestal_1554011"
    },
    {
      "link_thumb": "https://live.staticflickr.com/65535/51809679254_43aa5680a8_n.jpg",
      "link_img": "https://live.staticflickr.com/65535/51809679254_dc9156e859_o.png",
      "id_image": "pedestal_5706607"
    }
  ]
}